django_in_memory_models-1.0.5.dist-info/DESCRIPTION.rst
django_in_memory_models-1.0.5.dist-info/METADATA
django_in_memory_models-1.0.5.dist-info/RECORD
django_in_memory_models-1.0.5.dist-info/WHEEL
django_in_memory_models-1.0.5.dist-info/metadata.json
django_in_memory_models-1.0.5.dist-info/top_level.txt
in_memory/__init__.py
in_memory/apps.py
in_memory/fields.py
in_memory/models.py
in_memory/tests.py
in_memory/views.py
in_memory/__pycache__/__init__.cpython-36.pyc
in_memory/__pycache__/fields.cpython-36.pyc
in_memory/__pycache__/models.cpython-36.pyc
in_memory/redis/__init__.py
in_memory/redis/fields.py
in_memory/redis/models.py
in_memory/ssdb/__init__.py
in_memory/ssdb/fields.py
in_memory/ssdb/models.py
in_memory/ssdb/utils.py
in_memory/ssdb/__pycache__/__init__.cpython-36.pyc
in_memory/ssdb/__pycache__/fields.cpython-36.pyc
in_memory/ssdb/__pycache__/models.cpython-36.pyc
in_memory/ssdb/__pycache__/utils.cpython-36.pyc
